CHANGELOG.txt
LICENCE.txt
MANIFEST.in
README.md
README.txt
setup.py
docs/conf.py
docs/_build/html/_sources/index.rst.txt
docs/_build/html/_sources/modules.rst.txt
docs/_build/html/_sources/torch_airflow_sdk.decorators.rst.txt
docs/_build/html/_sources/torch_airflow_sdk.operators.rst.txt
docs/_build/html/_sources/torch_airflow_sdk.rst.txt
docs/_build/html/_sources/torch_airflow_sdk.utils.rst.txt
examples/dags/dag_1.py
examples/dags/dag_2.py
torch_airflow_sdk/__init__.py
torch_airflow_sdk/dag.py
torch_airflow_sdk/initialiser.py
torch_airflow_sdk.egg-info/PKG-INFO
torch_airflow_sdk.egg-info/SOURCES.txt
torch_airflow_sdk.egg-info/dependency_links.txt
torch_airflow_sdk.egg-info/requires.txt
torch_airflow_sdk.egg-info/top_level.txt
torch_airflow_sdk/decorators/__init__.py
torch_airflow_sdk/decorators/handle_callback.py
torch_airflow_sdk/decorators/job.py
torch_airflow_sdk/decorators/span.py
torch_airflow_sdk/operators/__init__.py
torch_airflow_sdk/operators/span_operator.py
torch_airflow_sdk/operators/torch_initialiser_operator.py
torch_airflow_sdk/utils/__init__.py
torch_airflow_sdk/utils/callback.py
torch_airflow_sdk/utils/torch_client.py