Metadata-Version: 2.1
Name: torch-airflow-sdk
Version: 0.1.1
Summary: Accel-data Torch Airflow SDK.  Acceldata Torch is a complete solution to observe the quality of the data present in your data lake and warehouse. Using Torch, you can ensure that high-quality data backs your business decisions.
Home-page: UNKNOWN
Author: acceldata
Author-email: support@acceldata.io
License: Apache Software License
Keywords: acceldata-torch
Platform: UNKNOWN
Classifier: Development Status :: 3 - Alpha
Classifier: Intended Audience :: Developers
Classifier: Operating System :: OS Independent
Classifier: License :: OSI Approved :: Apache Software License
Classifier: Programming Language :: Python :: 3
